ecdh/__init__.py
ecdh/__main__.py
ecdh/cell.py
ecdh/conf.py
ecdh/log.py
ecdh/plot.py
ecdh/utils.py
ecdh/whitaker_despiker_algorithm.py
ecdh/readers/BatSmall.py
ecdh/readers/BioLogic.py
ecdh/readers/Neware.py
ecdh/readers/Processed.py
ecdh/readers/__init__.py
ecdh/readers/testing.py
ecdh-0.1.5.dist-info/LICENSE.txt
ecdh-0.1.5.dist-info/METADATA
ecdh-0.1.5.dist-info/WHEEL
ecdh-0.1.5.dist-info/entry_points.txt
ecdh-0.1.5.dist-info/top_level.txt
ecdh-0.1.5.dist-info/RECORD
