Metadata-Version: 2.1
Name: ecdh
Version: 0.1.5
Summary: ElectroChemical Data Handler
Home-page: https://github.com/amundmr/ecdh
Author: Amund Raniseth
Author-email: amund.raniseth@gmail.com
License: GNU General Public License v3.0
Download-URL: https://github.com/amundmr/ecdh/archive/refs/tags/v0.1.5.tar.gz
Keywords: Electrochemical,battery,cell,datareader,dataplotter,reader,plotter
Platform: UNKNOWN
Classifier: Development Status :: 3 - Alpha
Classifier: Intended Audience :: Developers
Classifier: Topic :: Software Development :: Build Tools
Classifier: License :: OSI Approved :: GNU General Public License v3 (GPLv3)
Classifier: Programming Language :: Python :: 3
Classifier: Programming Language :: Python :: 3.4
Classifier: Programming Language :: Python :: 3.5
Classifier: Programming Language :: Python :: 3.6
Classifier: Programming Language :: Python :: 3.7
Classifier: Programming Language :: Python :: 3.8
Classifier: Programming Language :: Python :: 3.9
Requires-Dist: matplotlib
Requires-Dist: numpy
Requires-Dist: pandas
Requires-Dist: scipy
Requires-Dist: toml
